textunwrap/__init__.py
textunwrap/cli.py
textunwrap/textunwrap.py
textunwrap/textwrap.py
textunwrap-0.1.3.dist-info/AUTHORS.rst
textunwrap-0.1.3.dist-info/LICENSE
textunwrap-0.1.3.dist-info/METADATA
textunwrap-0.1.3.dist-info/WHEEL
textunwrap-0.1.3.dist-info/entry_points.txt
textunwrap-0.1.3.dist-info/top_level.txt
textunwrap-0.1.3.dist-info/RECORD
