Metadata-Version: 2.1
Name: textunwrap
Version: 0.1.3
Summary: Tries to reverse textwrap.wrap.
Home-page: https://github.com/JulienPalard/textunwrap
Author: Julien Palard
Author-email: julien@palard.fr
License: MIT
Keywords: textunwrap
Platform: UNKNOWN
Classifier: Development Status :: 2 - Pre-Alpha
Classifier: Intended Audience :: Developers
Classifier: License :: OSI Approved :: MIT License
Classifier: Natural Language :: English
Classifier: Programming Language :: Python :: 3
